decomp2dbg/__init__.py
decomp2dbg/__main__.py
decomp2dbg/d2d.py
decomp2dbg/installer.py
decomp2dbg/utils.py
decomp2dbg/clients/__init__.py
decomp2dbg/clients/client.py
decomp2dbg/clients/gdb/__init__.py
decomp2dbg/clients/gdb/decompiler_pane.py
decomp2dbg/clients/gdb/gdb_client.py
decomp2dbg/clients/gdb/gef_client.py
decomp2dbg/clients/gdb/pwndbg_client.py
decomp2dbg/clients/gdb/symbol_mapper.py
decomp2dbg/clients/gdb/utils.py
decomp2dbg/decompilers/server_template.py
decomp2dbg/decompilers/d2d_angr/__init__.py
decomp2dbg/decompilers/d2d_angr/d2d_angr.py
decomp2dbg/decompilers/d2d_angr/server.py
decomp2dbg/decompilers/d2d_binja/__init__.py
decomp2dbg/decompilers/d2d_binja/d2d_binja.py
decomp2dbg/decompilers/d2d_binja/plugin.json
decomp2dbg/decompilers/d2d_binja/server.py
decomp2dbg/decompilers/d2d_ida/d2d_ida.py
decomp2dbg/decompilers/d2d_ida/d2d_ida/__init__.py
decomp2dbg/decompilers/d2d_ida/d2d_ida/plugin.py
decomp2dbg/decompilers/d2d_ida/d2d_ida/server.py
decomp2dbg-3.14.1.dist-info/LICENSE
decomp2dbg-3.14.1.dist-info/METADATA
decomp2dbg-3.14.1.dist-info/WHEEL
decomp2dbg-3.14.1.dist-info/entry_points.txt
decomp2dbg-3.14.1.dist-info/top_level.txt
decomp2dbg-3.14.1.dist-info/RECORD
