Metadata-Version: 2.1
Name: decomp2dbg
Version: 3.14.1
Summary: Symbol syncing framework for decompilers and debuggers
Home-page: https://github.com/mahaloz/decomp2dbg
License: BSD 2 Clause
Classifier: License :: OSI Approved :: BSD License
Classifier: Programming Language :: Python :: 3
Classifier: Programming Language :: Python :: 3.6
Requires-Python: >=3.5
License-File: LICENSE
Requires-Dist: sortedcontainers
Requires-Dist: pyelftools
Requires-Dist: libbs >=0.12.0
